resume_ats/__init__.py
resume_ats/core.py
resume_ats/enhanced.py
resume_ats/enhanced_cli.py
resume_ats/pdf_report_generator.py
resume_ats/pdf_reporter.py
resume_ats/resume_anonymizer.py
resume_ats/resume_comparer.py
resume_ats/resume_version_tracker.py
resume_ats/utils.py
resume_ats_plugin-0.2.0.dist-info/licenses/LICENSE
resume_ats_plugin-0.2.0.dist-info/METADATA
resume_ats_plugin-0.2.0.dist-info/WHEEL
resume_ats_plugin-0.2.0.dist-info/entry_points.txt
resume_ats_plugin-0.2.0.dist-info/top_level.txt
resume_ats_plugin-0.2.0.dist-info/RECORD
