Metadata-Version: 2.4
Name: resume-ats-plugin
Version: 0.2.0
Summary: A plugin to analyze and optimize resumes for Applicant Tracking Systems (ATS)
Author-email: Kabhishek18 <developer@kabhishek18.com>
License: MIT
Project-URL: Homepage, https://github.com/yourusername/resume-ats-plugin
Project-URL: Bug Tracker, https://github.com/yourusername/resume-ats-plugin/issues
Classifier: Programming Language :: Python :: 3
Classifier: License :: OSI Approved :: MIT License
Classifier: Operating System :: OS Independent
Classifier: Development Status :: 4 - Beta
Classifier: Intended Audience :: Developers
Classifier: Topic :: Office/Business
Classifier: Topic :: Text Processing :: Markup
Requires-Python: >=3.7
License-File: LICENSE
Requires-Dist: pypdf>=3.15.0
Requires-Dist: python-docx>=0.8.11
Requires-Dist: nltk>=3.6.0
Requires-Dist: spacy>=3.0.0
Requires-Dist: scikit-learn>=1.0.0
Requires-Dist: matplotlib>=3.5.0
Requires-Dist: reportlab>=3.6.0
Requires-Dist: difflib>=0.0.0
Requires-Dist: numpy>=1.20.0
Provides-Extra: dev
Requires-Dist: pytest>=7.0.0; extra == "dev"
Requires-Dist: black>=22.1.0; extra == "dev"
Requires-Dist: isort>=5.10.0; extra == "dev"
Requires-Dist: mypy>=0.910; extra == "dev"
Dynamic: license-file
